[
{
"word": "telefono"
}, 
{
"word": "studento"
},
{
"word": "universitato"
},
{
"word": "profesoro"
}, 
{
"word": "tabako"
}, 
{
"word": "televido"
}, 
{
"word": "teatro"
}, 
{
"word": "portreto"
}, 
{
"word": "domo"
}, 
{
"word": "homo"
}, 
{
"word": "frukto"
}, 
{
"word": "traktoro"
}, 
{
"word": "divano"
}, 
{
"word": "lampo"
},
{
"word": "bluo"
},
{
"word": "abismo"
},
{
"word": "abĵuro"
},
{
"word": "aboli"
},
{
"word": "abolicio"
},
{
"word": "acetono"
},
{
"word": "adhero"
},
{
"word": "aktinio"
}
]
